autogluon/assistant/__init__.py
autogluon/assistant/coding_agent.py
autogluon/assistant/constants.py
autogluon/assistant/rich_logging.py
autogluon/assistant/utils.py
autogluon/assistant/agents/__init__.py
autogluon/assistant/agents/base_agent.py
autogluon/assistant/agents/coder_agent.py
autogluon/assistant/agents/data_perception_agent.py
autogluon/assistant/agents/description_file_retriever_agent.py
autogluon/assistant/agents/error_analyzer_agent.py
autogluon/assistant/agents/executer_agent.py
autogluon/assistant/agents/reranker_agent.py
autogluon/assistant/agents/retriever_agent.py
autogluon/assistant/agents/task_descriptor_agent.py
autogluon/assistant/agents/tool_selector_agent.py
autogluon/assistant/agents/utils.py
autogluon/assistant/cli/__init__.py
autogluon/assistant/cli/app.py
autogluon/assistant/configs/default.yaml
autogluon/assistant/llm/__init__.py
autogluon/assistant/llm/anthropic_chat.py
autogluon/assistant/llm/azure_openai_chat.py
autogluon/assistant/llm/base_chat.py
autogluon/assistant/llm/bedrock_chat.py
autogluon/assistant/llm/llm_factory.py
autogluon/assistant/llm/openai_chat.py
autogluon/assistant/managers/__init__.py
autogluon/assistant/managers/manager.py
autogluon/assistant/prompts/__init__.py
autogluon/assistant/prompts/base_prompt.py
autogluon/assistant/prompts/bash_coder_prompt.py
autogluon/assistant/prompts/description_file_retriever_prompt.py
autogluon/assistant/prompts/error_analyzer_prompt.py
autogluon/assistant/prompts/executer_prompt.py
autogluon/assistant/prompts/python_coder_prompt.py
autogluon/assistant/prompts/python_reader_prompt.py
autogluon/assistant/prompts/reranker_prompt.py
autogluon/assistant/prompts/retriever_prompt.py
autogluon/assistant/prompts/task_descriptor_prompt.py
autogluon/assistant/prompts/tool_selector_prompt.py
autogluon/assistant/prompts/utils.py
autogluon/assistant/tools_registry/__init__.py
autogluon/assistant/tools_registry/indexing.py
autogluon/assistant/tools_registry/registry.py
autogluon_assistant-1.0.0.dist-info/licenses/LICENSE
autogluon_assistant-1.0.0.dist-info/licenses/NOTICE
autogluon_assistant-1.0.0.dist-info/METADATA
autogluon_assistant-1.0.0.dist-info/WHEEL
autogluon_assistant-1.0.0.dist-info/entry_points.txt
autogluon_assistant-1.0.0.dist-info/top_level.txt
autogluon_assistant-1.0.0.dist-info/RECORD
