Metadata-Version: 2.4
Name: autogluon.assistant
Version: 1.0.0
Summary: Multi Agent System for Multimodal ML Automation
Author: AutoGluon Community
Project-URL: Homepage, https://github.com/autogluon/autogluon-assistant
Requires-Python: <3.12,>=3.8
License-File: LICENSE
License-File: NOTICE
Requires-Dist: langgraph
Requires-Dist: accelerate<1.0
Requires-Dist: autogluon==1.2.0
Requires-Dist: autogluon.tabular[skex]==1.2.0
Requires-Dist: chardet>=5.2.0
Requires-Dist: FlagEmbedding>=1.3.5
Requires-Dist: faiss-cpu
Requires-Dist: importlib-resources>=6.4.5
Requires-Dist: langchain>=0.3.3
Requires-Dist: langchain_openai>=0.2.2
Requires-Dist: langchain-anthropic>=0.3.15
Requires-Dist: langchain_aws>=0.2.2
Requires-Dist: pydantic>=2.9.2
Requires-Dist: hydra-core>=1.3
Requires-Dist: matplotlib>=3.9.2
Requires-Dist: typer>=0.12.5
Requires-Dist: rich>=13.8.1
Requires-Dist: s3fs
Requires-Dist: flask>=2.2
Requires-Dist: fsspec
Requires-Dist: joblib>=1.4.2
Requires-Dist: python-calamine
Requires-Dist: tenacity>=8.2.2
Requires-Dist: transformers<=4.49.0
Requires-Dist: pandas>=2.2
Requires-Dist: streamlit>=1.37
Requires-Dist: streamlit-aggrid>=1.0.2
Requires-Dist: streamlit-extras>=0.4
Requires-Dist: psutil>=5.9.8
Requires-Dist: peft>=0.15.2
Requires-Dist: opencv-python
Requires-Dist: fastmcp>=2.0.0
Requires-Dist: aiohttp>=3.8.0
Requires-Dist: requests>=2.28.0
Requires-Dist: boto3>=1.28.0
Requires-Dist: mcp>=0.1.0
Provides-Extra: dev
Requires-Dist: black>=24; extra == "dev"
Requires-Dist: GitRepo>=1; extra == "dev"
Requires-Dist: pytest>=7; extra == "dev"
Requires-Dist: pytest-asyncio>=0.21.0; extra == "dev"
Requires-Dist: isort; extra == "dev"
Requires-Dist: ruff==0.4; extra == "dev"
Dynamic: license-file
